echo.py
py_echo-1.0.2.dist-info/METADATA
py_echo-1.0.2.dist-info/WHEEL
py_echo-1.0.2.dist-info/top_level.txt
py_echo-1.0.2.dist-info/RECORD
