Metadata-Version: 2.1
Name: py-echo
Version: 1.0.2
Summary: stylize prints with colors, backgrounds, and styles
Home-page: https://github.com/murad-sinatra/
Author: Murad Sinatra
Author-email: muradmorshedd@gmail.com
License: UNKNOWN
Platform: UNKNOWN
